deepchecks_llm_client/__init__.py
deepchecks_llm_client/api.py
deepchecks_llm_client/client.py
deepchecks_llm_client/data_types.py
deepchecks_llm_client/exceptions.py
deepchecks_llm_client/hadron_auth.py
deepchecks_llm_client/otel.py
deepchecks_llm_client/otel_threading_patch.py
deepchecks_llm_client/utils.py
deepchecks_llm_client/examples/__init__.py
deepchecks_llm_client/examples/usage.py
deepchecks_llm_client/sdk/__init__.py
deepchecks_llm_client/sdk/langchain/__init__.py
deepchecks_llm_client/sdk/langchain/callbacks/__init__.py
deepchecks_llm_client/sdk/langchain/callbacks/deepchecks_callback_handler.py
deepchecks_llm_client-0.40.1.dist-info/METADATA
deepchecks_llm_client-0.40.1.dist-info/WHEEL
deepchecks_llm_client-0.40.1.dist-info/top_level.txt
deepchecks_llm_client-0.40.1.dist-info/RECORD
