Metadata-Version: 2.4
Name: deepchecks-llm-client
Version: 0.40.1
Summary: The SDK client for communicating with Deepchecks LLM service
Author-email: deepchecks <info@deepchecks.com>
Classifier: Programming Language :: Python :: 3
Classifier: License :: OSI Approved :: MIT License
Classifier: Operating System :: OS Independent
Requires-Python: >=3.8
Requires-Dist: httpx
Requires-Dist: openai
Requires-Dist: dunamai
Requires-Dist: pandas
Requires-Dist: pytz
Provides-Extra: langchain
Requires-Dist: langchain; extra == "langchain"
Provides-Extra: sagemaker
Requires-Dist: sagemaker<3.0.0,>=2.237.0; extra == "sagemaker"
Provides-Extra: hadron
Requires-Dist: sagemaker<3.0.0,>=2.237.0; extra == "hadron"
Provides-Extra: otel
Requires-Dist: opentelemetry-api; extra == "otel"
Requires-Dist: opentelemetry-sdk; extra == "otel"
Requires-Dist: litellm; extra == "otel"
Requires-Dist: openinference-instrumentation-crewai; extra == "otel"
Requires-Dist: openinference-instrumentation-litellm; extra == "otel"
Requires-Dist: openinference-instrumentation-langchain; extra == "otel"
